Metadata-Version: 1.0
Name: gaunbi-distributions
Version: 0.1
Summary: Gaussian and Binomial distributions
Home-page: UNKNOWN
Author: Esther Ye
Author-email: UNKNOWN
License: UNKNOWN
Platform: UNKNOWN
